usim800/Communicate.py
usim800/__init__.py
usim800/usim800.py
usim800/Info/__init__.py
usim800/Info/info.py
usim800/Parser/ATParser.py
usim800/Parser/JsonParser.py
usim800/Parser/__init__.py
usim800/Parser/stack.py
usim800/Parser/test.py
usim800/Request/Request.py
usim800/Request/__init__.py
usim800/Sms/__init__.py
usim800/Sms/sms.py
usim800-0.0.7.dist-info/LICENSE
usim800-0.0.7.dist-info/METADATA
usim800-0.0.7.dist-info/WHEEL
usim800-0.0.7.dist-info/top_level.txt
usim800-0.0.7.dist-info/RECORD
